apicli/__init__.py
apicli/api.py
apicli/defaults.py
apicli/fields.py
apicli/model.py
apicli/namespace.py
apicli/route.py
apicli-0.0.4.dist-info/METADATA
apicli-0.0.4.dist-info/WHEEL
apicli-0.0.4.dist-info/top_level.txt
apicli-0.0.4.dist-info/RECORD
