Metadata-Version: 2.1
Name: apicli
Version: 0.0.4
Summary: allow using a common code-base to create a REST API and a CLI
Home-page: https://github.com/sylvan-le-deunff/apicli
Author: Sylvan Le Deunff
Author-email: sledeunf@gmail.com
License: UNKNOWN
Platform: UNKNOWN
Classifier: Programming Language :: Python :: 3
Classifier: License :: OSI Approved :: MIT License
Classifier: Operating System :: OS Independent
Requires-Python: >=3.6
